{
  "mcu": "STM32F405",
  "board": "CLRACINGF4",
  "manufacturer": "CLRA",
  "uart_ports": [
    {
      "index": 1,
      "tx_pin": "PA9",
      "rx_pin": "PA10"
    },
    {
      "index": 3,
      "tx_pin": "PB10",
      "rx_pin": "PB11"
    },
    {
      "index": 4,
      "tx_pin": "PA0",
      "rx_pin": "PA1"
    },
    {
      "index": 6,
      "tx_pin": "PC6",
      "rx_pin": "PC7"
    }
  ],
  "spi_ports": [
    {
      "index": 1,
      "sclk_pin": "PA5",
      "miso_pin": "PA6",
      "mosi_pin": "PA7"
    },
    {
      "index": 2,
      "sclk_pin": "PB13",
      "miso_pin": "PB14",
      "mosi_pin": "PB15"
    },
    {
      "index": 3,
      "sclk_pin": "PC10",
      "miso_pin": "PC11",
      "mosi_pin": "PC12"
    }
  ],
  "beeper_pins": [
    {
      "index": 1,
      "pin": "PB4"
    }
  ],
  "motor_pins": [
    {
      "index": 1,
      "pin": "PB0"
    },
    {
      "index": 2,
      "pin": "PB1"
    },
    {
      "index": 3,
      "pin": "PA3"
    },
    {
      "index": 4,
      "pin": "PA2"
    },
    {
      "index": 5,
      "pin": "PB8"
    }
  ],
  "led_pins": [
    {
      "index": 1,
      "pin": "PB5"
    }
  ],
  "inverter_pins": [
    {
      "index": 1,
      "pin": "PC0"
    }
  ],
  "usb_detect_pin": "PC5",
  "battery_pin": {
    "pin": "PC2",
    "scale": 0
  },
  "current_pin": {
    "pin": "PC1",
    "scale": 250
  },
  "gyros": [
    {
      "index": 1,
      "exti_pin": "PC4",
      "port": 1,
      "cs_pin": "PA4"
    }
  ],
  "osd": {
    "port": 3,
    "cs_pin": "PA15"
  },
  "data_flash": {
    "port": 3,
    "cs_pin": "PB3"
  },
  "sd_card": {
    "port": 2,
    "cs_pin": "PB12"
  }
}
